{
  "version": "6.0.1",
  "build": "10A523",
  "released": "2012-10-29",
  "beta": false,
  "devices": {
    "iPhone2,1": {
      "ipsw": "http://appldnld.apple.com/iOS6/041-7949.20121101.Ortn5/iPhone2,1_6.0.1_10A523_Restore.ipsw"
    },
    "iPhone3,1": {
      "ipsw": "http://appldnld.apple.com/iOS6/041-7950.20121101.Lmr45/iPhone3,1_6.0.1_10A523_Restore.ipsw"
    },
    "iPhone3,2": {
      "ipsw": "http://appldnld.apple.com/iOS6/041-7951.20121101.GetM4/iPhone3,2_6.0.1_10A523_Restore.ipsw"
    },
    "iPhone3,3": {
      "ipsw": "http://appldnld.apple.com/iOS6/041-7952.20121101.aClm5/iPhone3,3_6.0.1_10A523_Restore.ipsw"
    },
    "iPhone4,1": {
      "ipsw": "http://appldnld.apple.com/iOS6/041-7953.20121101.Apmtr/iPhone4,1_6.0.1_10A523_Restore.ipsw"
    },
    "iPad2,1": {
      "ipsw": "http://appldnld.apple.com/iOS6/041-7942.20121101.Intn3/iPad2,1_6.0.1_10A523_Restore.ipsw"
    },
    "iPad2,2": {
      "ipsw": "http://appldnld.apple.com/iOS6/041-7945.20121101.Ofr42/iPad2,2_6.0.1_10A523_Restore.ipsw"
    },
    "iPad2,3": {
      "ipsw": "http://appldnld.apple.com/iOS6/041-7946.20121101.Mxs3e/iPad2,3_6.0.1_10A523_Restore.ipsw"
    },
    "iPad2,4": {
      "ipsw": "http://appldnld.apple.com/iOS6/041-7944.20121101.Tre3r/iPad2,4_6.0.1_10A523_Restore.ipsw"
    },
    "iPad3,1": {
      "ipsw": "http://appldnld.apple.com/iOS6/041-7940.20121101.Sand6/iPad3,1_6.0.1_10A523_Restore.ipsw"
    },
    "iPad3,2": {
      "ipsw": "http://appldnld.apple.com/iOS6/041-7941.20121101.Sami5/iPad3,2_6.0.1_10A523_Restore.ipsw"
    },
    "iPad3,3": {
      "ipsw": "http://appldnld.apple.com/iOS6/041-7943.20121101.DuI5t/iPad3,3_6.0.1_10A523_Restore.ipsw"
    },
    "iPod4,1": {
      "ipsw": "http://appldnld.apple.com/iOS6/041-7439.20121101.rgt54/iPod4,1_6.0.1_10A523_Restore.ipsw"
    },
    "iPod5,1": {
      "ipsw": "http://appldnld.apple.com/iOS6/041-7438.20121101.Usre4/iPod5,1_6.0.1_10A523_Restore.ipsw"
    }
  },
  "osStr": "iOS",
  "uniqueBuild": "10A523"
}